oncopipe/__init__.py
oncopipe/__version__.py
oncopipe-1.0.12.dist-info/METADATA
oncopipe-1.0.12.dist-info/WHEEL
oncopipe-1.0.12.dist-info/top_level.txt
oncopipe-1.0.12.dist-info/RECORD
